statsbiblioteket/harvest/__init__.py
statsbiblioteket/harvest/clients.py
statsbiblioteket/harvest/contacts.py
statsbiblioteket/harvest/expense_categories.py
statsbiblioteket/harvest/expenses.py
statsbiblioteket/harvest/harvest.py
statsbiblioteket/harvest/invoices.py
statsbiblioteket/harvest/projects.py
statsbiblioteket/harvest/rest.py
statsbiblioteket/harvest/task_assignments.py
statsbiblioteket/harvest/tasks.py
statsbiblioteket/harvest/timetracking.py
statsbiblioteket/harvest/users.py
statsbiblioteket.harvest-1.1.4rc0.dist-info/DESCRIPTION.rst
statsbiblioteket.harvest-1.1.4rc0.dist-info/METADATA
statsbiblioteket.harvest-1.1.4rc0.dist-info/RECORD
statsbiblioteket.harvest-1.1.4rc0.dist-info/WHEEL
statsbiblioteket.harvest-1.1.4rc0.dist-info/entry_points.txt
statsbiblioteket.harvest-1.1.4rc0.dist-info/metadata.json
statsbiblioteket.harvest-1.1.4rc0.dist-info/top_level.txt
