Metadata-Version: 2.0
Name: statsbiblioteket.harvest
Version: 1.1.4rc0
Summary: Harvest api client
Home-page: https://github.com/statsbiblioteket/python-harvest
Author: Asger Askov Blekinge
Author-email: asger.askov.blekinge@gmail.com
License: MIT License
Keywords: harvestapp timetracking api
Platform: UNKNOWN
Classifier: Development Status :: 5 - Production/Stable
Classifier: Environment :: Console
Classifier: Intended Audience :: Developers
Classifier: Natural Language :: English
Classifier: Operating System :: POSIX :: Linux
Classifier: Programming Language :: Python :: 3.5
Classifier: Topic :: Software Development :: Libraries
Classifier: Topic :: Internet :: WWW/HTTP :: Site Management
Classifier: Topic :: Utilities
Classifier: License :: OSI Approved :: MIT License
Requires-Dist: argparse
Requires-Dist: inflection
Requires-Dist: python-log-indenter
Requires-Dist: requests
Requires-Dist: requests-oauthlib
Requires-Dist: sqlalchemy
Requires-Dist: typing
